agentic/__init__.py
agentic/actor_agents.py
agentic/agentic_secrets.py
agentic/cli.py
agentic/colors.py
agentic/events.py
agentic/file_cache.py
agentic/fix_console.py
agentic/llm.py
agentic/model_mock.py
agentic/models.py
agentic/runner.py
agentic/settings.py
agentic/swarm/__init__.py
agentic/swarm/core.py
agentic/swarm/types.py
agentic/swarm/util.py
agentic/swarm/repl/__init__.py
agentic/swarm/repl/repl.py
agentic/tools/__init__.py
agentic/tools/auth_rest_api_tool.py
agentic/tools/automatic_tools.py
agentic/tools/base.py
agentic/tools/database_tool.py
agentic/tools/file_download.py
agentic/tools/google_news.py
agentic/tools/linkedin_tool.py
agentic/tools/registry.py
agentic/tools/rest_tool_v2.py
agentic/tools/scaleserp_browser.py
agentic/tools/text_to_speech_tool.py
agentic/tools/unit_test_tool.py
agentic/tools/weather_tool.py
agentic/ui/__init__.py
agentic/ui/chat.py
agentic/ui/dual_chat.py
agentic/ui/game.py
agentic_examples/__init__.py
agentic_examples/basic_agent.py
agentic_examples/database_agent.py
agentic_examples/dynamic.py
agentic_examples/handoff_demo.py
agentic_examples/human_in_the_loop.py
agentic_examples/news_demo.py
agentic_examples/people_researcher.py
agentic_examples/podcast.py
agentic_examples/testing.py
aaagentic-0.1.1.dist-info/METADATA
aaagentic-0.1.1.dist-info/WHEEL
aaagentic-0.1.1.dist-info/entry_points.txt
aaagentic-0.1.1.dist-info/top_level.txt
aaagentic-0.1.1.dist-info/RECORD
