Metadata-Version: 2.2
Name: aaagentic
Version: 0.1.1
Summary: An opinionated framework for building AI Agents
Requires-Python: >=3.12
Requires-Dist: google-news-feed>=1.1.0
Requires-Dist: googlenewsdecoder>=0.1.7
Requires-Dist: html2text>=2024.2.26
Requires-Dist: jinja2>=3.1.5
Requires-Dist: pyyaml>=6.0.2
Requires-Dist: streamlit>=1.41.1
Requires-Dist: swarm
Requires-Dist: thespian>=4.0.0
Requires-Dist: litellm>=1.60.2
Requires-Dist: html2text>=2024.2.26
Requires-Dist: typer>=0.15.1
Requires-Dist: cryptography>=44.0.0
Requires-Dist: psycopg2-binary>=2.9.9
Requires-Dist: sqlalchemy>=2.0.26
Requires-Dist: ray>=2.42.0
Requires-Dist: debugpy>=1.8.0
Requires-Dist: aiofiles>=24.1.0
Requires-Dist: pytest-asyncio>=0.25.3
Provides-Extra: dev
Requires-Dist: pytest; extra == "dev"
Requires-Dist: black; extra == "dev"
